YunYuanshengJiagouBaipishuGaV20721Fix1/README.md
YunYuanshengJiagouBaipishuGaV20721Fix1/__init__.py
YunYuanshengJiagouBaipishuGaV20721Fix1/__main__.py
YunYuanshengJiagouBaipishuGaV20721Fix1/file.pdf
YunYuanshengJiagouBaipishuGaV20721Fix1/index.html
yun_yuansheng_jiagou_baipishu_ga_v20_7_21_fix1-2025.3.25.0.dist-info/METADATA
yun_yuansheng_jiagou_baipishu_ga_v20_7_21_fix1-2025.3.25.0.dist-info/WHEEL
yun_yuansheng_jiagou_baipishu_ga_v20_7_21_fix1-2025.3.25.0.dist-info/entry_points.txt
yun_yuansheng_jiagou_baipishu_ga_v20_7_21_fix1-2025.3.25.0.dist-info/top_level.txt
yun_yuansheng_jiagou_baipishu_ga_v20_7_21_fix1-2025.3.25.0.dist-info/RECORD
